{
  "products": [
    {
      "id": "1",
      "name": "Café americano",
      "price": 5,
      "image": "https://images.unsplash.com/photo-1504630083234-14187a9df0f5?ixlib=rb-1.2.1&ixid=MnwxMjA3fDB8MHxwaG90by1wYWdlfHx8fGVufDB8fHx8&auto=format&fit=crop&w=1470&q=80",
      "type": "Desayuno",
      "dateEntry": "15/09/22"
    },
    {
      "id": "2",
      "name": "Café con leche",
      "price": 7,
      "image": "https://images.unsplash.com/photo-1604423043122-00244f00e116?ixlib=rb-1.2.1&ixid=MnwxMjA3fDB8MHxwaG90by1wYWdlfHx8fGVufDB8fHx8&auto=format&fit=crop&w=387&q=80",
      "type": "Desayuno",
      "dateEntry": "15/09/22"
    },
    {
      "id": "3",
      "name": "Sandwich de jamón y queso",
      "price": 10,
      "image": "https://unareceta.com/wp-content/uploads/2017/02/sandwich-vegetal-640x427.jpg",
      "type": "Desayuno",
      "dateEntry": "15/09/22"
    },
    {
      "id": "4",
      "name": "Jugo de frutas natural",
      "price": 7,
      "image": "https://blog.creublanca.es/uploads/ea9297be6d16e543989fca96b7a839c3.jpg",
      "type": "Desayuno",
      "dateEntry": "15/09/22"
    },
    {
      "id": "5",
      "name": "Hamburguesa simple",
      "price": 10,
      "image": "https://media.istockphoto.com/photos/tasty-fast-food-cheeseburger-on-black-background-picture-id1339463771?k=20&m=1339463771&s=612x612&w=0&h=WgT6Ghgj1S6TwYWcUtJjqKLhnP9bQIkNHjOtDrUyUBw=",
      "type": "Almuerzo y cena",
      "dateEntry": "15/09/22"
    },
    {
      "id": "6",
      "name": "Hamburguesa doble",
      "price": 15,
      "image": "https://img.freepik.com/fotos-premium/hamburguesa-doble-lechuga-tomate-cebolla-queso-derretido_250927-603.jpg?w=826",
      "type": "Almuerzo y cena",
      "dateEntry": "15/09/22"
    },
    {
      "id": "7",
      "name": "Papas fritas",
      "price": 5,
      "image": "https://media.istockphoto.com/photos/french-fries-picture-id852412726?k=20&m=852412726&s=612x612&w=0&h=2c4BaLxd4SVReDNe235O5Rx3tD4rDFFrhWOSE1e4CdI=",
      "type": "Almuerzo y cena",
      "dateEntry": "15/09/22"
    },
    {
      "id": "8",
      "name": "Aros de cebolla",
      "price": 5,
      "image": "https://media.istockphoto.com/photos/selective-focus-fried-onion-rings-in-breadcrumbs-fried-in-oil-on-a-picture-id1399360606?k=20&m=1399360606&s=612x612&w=0&h=DUTUlmH5dZCI8jAJqNL1MPP0jXfqudsGI6xBKSoO3GM=",
      "type": "Almuerzo y cena",
      "dateEntry": "15/09/22"
    },
    {
      "id": "9",
      "name": "Agua 500ml",
      "price": 5,
      "image": "https://contents.mediadecathlon.com/p2156016/k$d7dcb09052e7fa71cac99de52a83e590/sq/965940.jpg?format=auto&f=800x0",
      "type": "Bebidas",
      "dateEntry": "15/09/22"
    },
    {
      "id": "10",
      "name": "Agua 750ml",
      "price": 7,
      "image": "https://media.istockphoto.com/photos/water-bottle-mockup-picture-id624125324?k=20&m=624125324&s=612x612&w=0&h=5bEH3720V3bXsNq--xqxT3__X9C6ctoa7o7F7sfUiG4=",
      "type": "Bebidas",
      "dateEntry": "15/09/22"
    },
    {
      "id": "11",
      "name": "Bebida/gaseosa 500ml",
      "price": 7,
      "image": "https://images.unsplash.com/photo-1527960471264-932f39eb5846?ixlib=rb-1.2.1&ixid=MnwxMjA3fDB8MHxwaG90by1yZWxhdGVkfDZ8fHxlbnwwfHx8fA%3D%3D&auto=format&fit=crop&w=500&q=60",
      "type": "Bebidas",
      "dateEntry": "15/09/22"
    },
    {
      "id": "12",
      "name": "Bebida/gaseosa 750ml",
      "price": 10,
      "image": "https://asphericnews.com/wp-content/uploads/2021/10/5-negative-effects-of-drinking-soda..jpg",
      "type": "Bebidas",
      "dateEntry": "15/09/22"
    }
  ],
  "users": [
    {
      "email": "mesero1@gmail.com",
      "password": "123456",
      "roles": {
        "admin": false,
        "chef": false
      },
      "id": 1
    },
    {
      "email": "chef1@gmail.com",
      "password": "123456",
      "roles": {
        "admin": false,
        "chef": true
      },
      "id": 2
    },
    {
      "email": "admin@gmail.com",
      "password": "123456",
      "roles": {
        "admin": true,
        "chef": false
      },
      "id": 3
    },
    {
      "email": "nesero2@gmail.com",
      "password": "123456",
      "roles": {
        "admin": false,
        "chef": false
      },
      "id": 4
    },
    {
      "email": "chef2@gmail.com",
      "password": "123456",
      "roles": {
        "admin": false,
        "chef": true
      },
      "id": 5
    }
  ],
  "orders": [
    {
      "userId": "1",
      "client": "Sandra",
      "products": [
        {
          "name": "Café con leche",
          "productId": "2",
          "qty": 1
        }
      ],
      "status": "delivered",
      "dateEntry": "2022-10-25T13:21:36.035Z",
      "id": 1
    },
    {
      "userId": "1",
      "client": "Katy",
      "products": [
        {
          "name": "Café con leche",
          "productId": "2",
          "qty": 1
        },
        {
          "name": "Café americano",
          "productId": "1",
          "qty": 2
        }
      ],
      "status": "delivering",
      "dateEntry": "2022-10-25T13:23:08.303Z",
      "id": 2
    },
    {
      "userId": "1",
      "client": "Gaby",
      "products": [
        {
          "name": "Café con leche",
          "productId": "2",
          "qty": 1
        },
        {
          "name": "Café americano",
          "productId": "1",
          "qty": 2
        }
      ],
      "status": "pending",
      "dateEntry": "2022-10-25T13:34:12.060Z",
      "id": 3
    }
  ]
}